[
  {
    "id": "1",
    "name": "Outr space 8",
    "key": "OS8",
    "type": "Cuộc thi",
    "startTime": "1/1/2024",
    "leader": "Võ Tuấn Tài",
    "status": "Đang diễn ra"
  },
  {
    "id": "2",
    "name": "Outr space 7",
    "key": "OS7",
    "type": "Cuộc thi",
    "startTime": "1/1/2023",
    "leader": "Lê Vũ Ngân Trúc",
    "status": "Đã kết thúc"
  },
  {
    "id": "3",
    "name": "Workshop D2D",
    "key": "D2D",
    "type": "Workshop",
    "startTime": "1/12/2023",
    "leader": "Võ Tuấn Tài",
    "status": "Đang diễn ra"
  },
  {
    "id": "4",
    "name": "Tuyển quân gen 13",
    "key": "G13",
    "type": "Cuộc thi",
    "startTime": "1/1/2024",
    "leader": "Võ Tuấn Tài",
    "status": "Đang diễn ra"
  },
  {
    "id": "5",
    "name": "Tuyển quân gen 12",
    "key": "G12",
    "type": "Cuộc thi",
    "startTime": "1/9/2022",
    "leader": "Lê Vũ Ngân Trúc",
    "status": "Đang diễn ra"
  },
  {
    "id": "6",
    "name": "Outr space 8",
    "key": "OS8",
    "type": "Cuộc thi",
    "startTime": "1/1/2024",
    "leader": "Võ Tuấn Tài",
    "status": "Đang diễn ra"
  },
  {
    "id": "7",
    "name": "Outr space 7",
    "key": "OS7",
    "type": "Cuộc thi",
    "startTime": "1/1/2023",
    "leader": "Lê Vũ Ngân Trúc",
    "status": "Đã kết thúc"
  },
  {
    "id": "8",
    "name": "Workshop D2D",
    "key": "D2D",
    "type": "Workshop",
    "startTime": "1/12/2023",
    "leader": "Võ Tuấn Tài",
    "status": "Đang diễn ra"
  },
  {
    "id": "9",
    "name": "Tuyển quân gen 13",
    "key": "G13",
    "type": "Cuộc thi",
    "startTime": "1/1/2024",
    "leader": "Võ Tuấn Tài",
    "status": "Đang diễn ra"
  },
  {
    "id": "10",
    "name": "Tuyển quân gen 12",
    "key": "G12",
    "type": "Cuộc thi",
    "startTime": "1/9/2022",
    "leader": "Lê Vũ Ngân Trúc",
    "status": "Đang diễn ra"
  },
  {
    "id": "11",
    "name": "Outr space 8",
    "key": "OS8",
    "type": "Cuộc thi",
    "startTime": "1/1/2024",
    "leader": "Võ Tuấn Tài",
    "status": "Đang diễn ra"
  },
  {
    "id": "12",
    "name": "Outr space 7",
    "key": "OS7",
    "type": "Cuộc thi",
    "startTime": "1/1/2023",
    "leader": "Lê Vũ Ngân Trúc",
    "status": "Đã kết thúc"
  },
  {
    "id": "13",
    "name": "Workshop D2D",
    "key": "D2D",
    "type": "Workshop",
    "startTime": "1/12/2023",
    "leader": "Võ Tuấn Tài",
    "status": "Đang diễn ra"
  },
  {
    "id": "14",
    "name": "Tuyển quân gen 13",
    "key": "G13",
    "type": "Cuộc thi",
    "startTime": "1/1/2024",
    "leader": "Võ Tuấn Tài",
    "status": "Đang diễn ra"
  },
  {
    "id": "15",
    "name": "Tuyển quân gen 12",
    "key": "G12",
    "type": "Cuộc thi",
    "startTime": "1/9/2022",
    "leader": "Lê Vũ Ngân Trúc",
    "status": "Đang diễn ra"
  }
]
